urbangrammar_graphics/__init__.py
urbangrammar_graphics/graphics.py
urbangrammar_graphics/test_graphics.py
urbangrammar_graphics-1.2.3.dist-info/LICENSE
urbangrammar_graphics-1.2.3.dist-info/METADATA
urbangrammar_graphics-1.2.3.dist-info/WHEEL
urbangrammar_graphics-1.2.3.dist-info/top_level.txt
urbangrammar_graphics-1.2.3.dist-info/RECORD
