Metadata-Version: 2.1
Name: urbangrammar-graphics
Version: 1.2.3
Summary: Visual style for Urban Grammar AI research project
Home-page: https://github.com/urbangrammarai/graphics
Author: Martin Fleischmann
Author-email: martin@martinfleischmann.net
License: UNKNOWN
Platform: UNKNOWN
Requires-Python: >=3.6
License-File: LICENSE
Requires-Dist: matplotlib
Requires-Dist: seaborn
Requires-Dist: numpy
Requires-Dist: contextily
